pypdf_seekers-0.1.3.dist-info/METADATA
pypdf_seekers-0.1.3.dist-info/WHEEL
pypdf_seekers-0.1.3.dist-info/license_files/LICENSE.txt
pypdf_seekers/__init__.py
pypdf_seekers/pypdf_seekers.cp312-win32.pyd
pypdf_seekers-0.1.3.dist-info/RECORD
