Metadata-Version: 2.1
Name: pypdf_seekers
Version: 0.1.3
Classifier: Programming Language :: Rust
Classifier: Programming Language :: Python :: Implementation :: CPython
Classifier: Programming Language :: Python :: Implementation :: PyPy
License-File: LICENSE.txt
Summary: Simple parser and information extractor from PDF documents based on keyword search functionality (powered by Rust)
Author: Tapas Das <dlaststark@gmail.com>
Author-email: Tapas Das <dlaststark@gmail.com>
License: MIT OR Apache-2.0
Requires-Python: >=3.8
Project-URL: Source Code, https://github.com/oss-rust-github-io/pdf-seekers.git
